dicergirl/dnd/__init__.py
dicergirl/dnd/adventurer.py
dicergirl/dnd/dndcards.py
dicergirl/dnd/dndutils.py
dicergirl/dnd/nbhandlers.py
dicergirl/plugins/dnd/__init__.py
dicergirl/plugins/dnd/adventurer.py
dicergirl/plugins/dnd/dndcards.py
dicergirl/plugins/dnd/dndutils.py
dicergirl/plugins/dnd/docimasy.py
dicergirl/plugins/dnd/nbhandlers.py
dicergirl_plugin_dnd-1.3.0.dist-info/METADATA
dicergirl_plugin_dnd-1.3.0.dist-info/WHEEL
dicergirl_plugin_dnd-1.3.0.dist-info/top_level.txt
dicergirl_plugin_dnd-1.3.0.dist-info/RECORD
