Metadata-Version: 2.1
Name: dicergirl-plugin-dnd
Version: 1.3.0
Summary: Dicergirl DND 模式插件
Home-page: https://gitee.com/unvisitor/dicergirl-plugin-dnd/
Author: Night Resurgent <fu050409@163.com>
Author-email: fu050409@163.com
License: Apache-2.0
Project-URL: Bug Tracker, https://gitee.com/unvisitor/dicer-plugins/issues
Classifier: Programming Language :: Python :: 3
Classifier: License :: OSI Approved :: Apache Software License
Classifier: Operating System :: OS Independent
Requires-Python: >=3
Requires-Dist: dicergirl
